[
  {
    "logo": "/education/logo_unileste.jpeg",
    "institution": "Centro Universitário do Leste de Minas Gerais - Unileste",
    "course": "Sistemas de Informação",
    "date": "ago 2022 - presente",
    "description": "Aprendizado no desenvolvimento de software em todas as etapas, banco de dados, modelagem e engenharia de software, inteligência artificial, entre outros.",
    "link": "https://unileste.catolica.edu.br/portal/",
    "technologies": [
      "C",
      "Java",
      "PHP",
      "Python",
      "JavaScript",
      "Node",
      "HTML",
      "CSS",
      "Boostrap",
      "PosgreSQL",
      "Mysql",
      "MongoDB"
    ]
  }
]
